ninja_parser.py
NinjaParser-0.0.1.dist-info/LICENSE
NinjaParser-0.0.1.dist-info/METADATA
NinjaParser-0.0.1.dist-info/WHEEL
NinjaParser-0.0.1.dist-info/entry_points.txt
NinjaParser-0.0.1.dist-info/top_level.txt
NinjaParser-0.0.1.dist-info/RECORD
