Metadata-Version: 2.1
Name: NinjaParser
Version: 0.0.1
Summary: Parse .ninja_log files and print statistics.
Home-page: https://github.com/keceli/NinjaParser
Author: Murat Keçeli
Author-email: keceli@gmail.com
License: UNKNOWN
Project-URL: Bug Tracker, https://github.com/keceli/NinjaParser/issues
Platform: UNKNOWN
Classifier: Programming Language :: Python :: 3
Classifier: License :: OSI Approved :: MIT License
Classifier: Operating System :: OS Independent
License-File: LICENSE
